apypie/__init__.py
apypie/action.py
apypie/api.py
apypie/example.py
apypie/exceptions.py
apypie/foreman.py
apypie/inflector.py
apypie/param.py
apypie/resource.py
apypie/route.py
apypie-0.7.1.dist-info/licenses/LICENSE
apypie-0.7.1.dist-info/METADATA
apypie-0.7.1.dist-info/WHEEL
apypie-0.7.1.dist-info/top_level.txt
apypie-0.7.1.dist-info/RECORD
